versions.py
program_versions-1.5.2.dist-info/DESCRIPTION.rst
program_versions-1.5.2.dist-info/METADATA
program_versions-1.5.2.dist-info/RECORD
program_versions-1.5.2.dist-info/WHEEL
program_versions-1.5.2.dist-info/entry_points.txt
program_versions-1.5.2.dist-info/metadata.json
program_versions-1.5.2.dist-info/top_level.txt
