Metadata-Version: 2.0
Name: program-versions
Version: 1.5.2
Summary: Know version changes of your favorites projects in your terminal.
Home-page: https://github.com/dupgit/versions
Author: Olivier Delhomme
Author-email: olivier.delhomme@free.fr
License: UNKNOWN
Keywords: version-checker version follower rss atom command-line
Platform: UNKNOWN
Classifier: Development Status :: 5 - Production/Stable
Classifier: Intended Audience :: Developers
Classifier: Intended Audience :: Information Technology
Classifier: Intended Audience :: System Administrators
Classifier: Intended Audience :: Science/Research
Classifier: Topic :: Software Development :: Version Control
Classifier: License :: OSI Approved :: GNU General Public License v3 or later (GPLv3+)
Classifier: Programming Language :: Python :: 2
Classifier: Programming Language :: Python :: 2.7
Classifier: Programming Language :: Python :: 3
Classifier: Programming Language :: Python :: 3.4
Classifier: Programming Language :: Python :: 3.5
Classifier: Programming Language :: Python :: 3.6
Requires-Dist: feedparser (>=5.1.3)
Requires-Dist: PyYAML (>=3.11)
